berkeleydb-stubs/__init__.pyi
berkeleydb-stubs/_berkeleydb.pyi
berkeleydb-stubs/db.pyi
berkeleydb-stubs/dbobj.pyi
berkeleydb-stubs/dbrecio.pyi
berkeleydb-stubs/dbshelve.pyi
berkeleydb-stubs/dbutils.pyi
berkeleydb_stubs-6.2.9.dist-info/METADATA
berkeleydb_stubs-6.2.9.dist-info/WHEEL
berkeleydb_stubs-6.2.9.dist-info/top_level.txt
berkeleydb_stubs-6.2.9.dist-info/RECORD
