Metadata-Version: 2.1
Name: berkeleydb-stubs
Version: 6.2.9
Summary: Typing stubs for Python Bindings for Oracle Berkeley DB
Home-page: https://github.com/eggplants/berkeleydb-stubs
Author: eggplants
Author-email: w10776e8w@yahoo.co.jp
License: UNKNOWN
Platform: UNKNOWN
Classifier: Intended Audience :: Developers
Classifier: Programming Language :: Python
Requires-Dist: berkeleydb
Provides-Extra: dev
Requires-Dist: black ; extra == 'dev'
Requires-Dist: flake8-black ; extra == 'dev'
Requires-Dist: mypy ; extra == 'dev'
Requires-Dist: flake8 ; extra == 'dev'
Requires-Dist: flake8-pyi ; extra == 'dev'
Requires-Dist: setuptools ; extra == 'dev'
Requires-Dist: wheel ; extra == 'dev'
